arkforge/__init__.py
arkforge/_base_client.py
arkforge/_http.py
arkforge/_rate_limiter.py
arkforge/_retry.py
arkforge/client.py
arkforge/config.py
arkforge/errors.py
arkforge/key_management.py
arkforge/version.py
arkforge/models/__init__.py
arkforge/models/common.py
arkforge/models/requests.py
arkforge/models/responses.py
arkforge-0.0.2.dist-info/METADATA
arkforge-0.0.2.dist-info/WHEEL
arkforge-0.0.2.dist-info/RECORD
